GerenYuquntiShijiandeBenzhi/Dockerfile
GerenYuquntiShijiandeBenzhi/README.md
GerenYuquntiShijiandeBenzhi/__init__.py
GerenYuquntiShijiandeBenzhi/__main__.py
GerenYuquntiShijiandeBenzhi/file.epub
GerenYuquntiShijiandeBenzhi/index.html
GerenYuquntiShijiandeBenzhi/css/__init__.py
GerenYuquntiShijiandeBenzhi/css/annotations.css
GerenYuquntiShijiandeBenzhi/css/main.css
GerenYuquntiShijiandeBenzhi/css/normalize.css
GerenYuquntiShijiandeBenzhi/css/popup.css
GerenYuquntiShijiandeBenzhi/font/__init__.py
GerenYuquntiShijiandeBenzhi/font/fontello.eot
GerenYuquntiShijiandeBenzhi/font/fontello.svg
GerenYuquntiShijiandeBenzhi/font/fontello.ttf
GerenYuquntiShijiandeBenzhi/font/fontello.woff
GerenYuquntiShijiandeBenzhi/img/__init__.py
GerenYuquntiShijiandeBenzhi/img/annotator-glyph-sprite.png
GerenYuquntiShijiandeBenzhi/img/annotator-icon-sprite.png
GerenYuquntiShijiandeBenzhi/img/apple-touch-icon.png
GerenYuquntiShijiandeBenzhi/img/cancelfullscreen.png
GerenYuquntiShijiandeBenzhi/img/close.png
GerenYuquntiShijiandeBenzhi/img/fullscreen.png
GerenYuquntiShijiandeBenzhi/img/loader.gif
GerenYuquntiShijiandeBenzhi/img/menu-icon.png
GerenYuquntiShijiandeBenzhi/img/save.png
GerenYuquntiShijiandeBenzhi/img/saved.png
GerenYuquntiShijiandeBenzhi/img/settings-s.png
GerenYuquntiShijiandeBenzhi/img/settings.png
GerenYuquntiShijiandeBenzhi/img/star.png
GerenYuquntiShijiandeBenzhi/js/__init__.py
GerenYuquntiShijiandeBenzhi/js/epub.js
GerenYuquntiShijiandeBenzhi/js/epub.min.js
GerenYuquntiShijiandeBenzhi/js/epub.min.map
GerenYuquntiShijiandeBenzhi/js/hooks.min.js
GerenYuquntiShijiandeBenzhi/js/hooks.min.map
GerenYuquntiShijiandeBenzhi/js/reader.js
GerenYuquntiShijiandeBenzhi/js/reader.js.map
GerenYuquntiShijiandeBenzhi/js/reader.min.js
GerenYuquntiShijiandeBenzhi/js/reader.min.map
GerenYuquntiShijiandeBenzhi/js/hooks/__init__.py
GerenYuquntiShijiandeBenzhi/js/hooks/extensions/__init__.py
GerenYuquntiShijiandeBenzhi/js/hooks/extensions/highlight.js
GerenYuquntiShijiandeBenzhi/js/libs/__init__.py
geren_yuqunti_shijiande_benzhi-2022.10.9.1.dist-info/METADATA
geren_yuqunti_shijiande_benzhi-2022.10.9.1.dist-info/WHEEL
geren_yuqunti_shijiande_benzhi-2022.10.9.1.dist-info/entry_points.txt
geren_yuqunti_shijiande_benzhi-2022.10.9.1.dist-info/top_level.txt
geren_yuqunti_shijiande_benzhi-2022.10.9.1.dist-info/RECORD
